<?xml version="1.0" encoding="UTF-8"?>
<!DOCTYPE mapper PUBLIC "-//mybatis.org//DTD Mapper 3.0//EN" "http://mybatis.org/dtd/mybatis-3-mapper.dtd">
<mapper namespace="com.humingfeng.mapper.SysPermissionMapper">
  <resultMap id="BaseResultMap" type="com.humingfeng.pojo.SysPermission">
    <!--
      WARNING - @mbg.generated
      This element is automatically generated by MyBatis Generator, do not modify.
    -->
    <id column="id" jdbcType="INTEGER" property="id" />
    <result column="menu_code" jdbcType="VARCHAR" property="menuCode" />
    <result column="menu_name" jdbcType="VARCHAR" property="menuName" />
    <result column="permission_code" jdbcType="VARCHAR" property="permissionCode" />
    <result column="permission_name" jdbcType="VARCHAR" property="permissionName" />
    <result column="required_permission" jdbcType="BIT" property="requiredPermission" />
  </resultMap>

  <resultMap id="permissionMap" type="com.humingfeng.model.One2Many">
    <id column="userId" property="userId"/>
    <result column="nickname" property="nickname"/>
    <result column="roleId" property="roleId"/>
    <result column="roleName" property="roleName"/>
    <collection property="menuList" ofType="String">
      <id column="menuCode" property="menuCode"/>
    </collection>
    <collection property="permissionList" ofType="String">
      <id column="permissionCode" property="permissionCode"/>
    </collection>
  </resultMap>
  <sql id="Example_Where_Clause">
    <!--
      WARNING - @mbg.generated
      This element is automatically generated by MyBatis Generator, do not modify.
    -->
    <where>
      <foreach collection="oredCriteria" item="criteria" separator="or">
        <if test="criteria.valid">
          <trim prefix="(" prefixOverrides="and" suffix=")">
            <foreach collection="criteria.criteria" item="criterion">
              <choose>
                <when test="criterion.noValue">
                  and ${criterion.condition}
                </when>
                <when test="criterion.singleValue">
                  and ${criterion.condition} #{criterion.value}
                </when>
                <when test="criterion.betweenValue">
                  and ${criterion.condition} #{criterion.value} and #{criterion.secondValue}
                </when>
                <when test="criterion.listValue">
                  and ${criterion.condition}
                  <foreach close=")" collection="criterion.value" item="listItem" open="(" separator=",">
                    #{listItem}
                  </foreach>
                </when>
              </choose>
            </foreach>
          </trim>
        </if>
      </foreach>
    </where>
  </sql>
  <sql id="Update_By_Example_Where_Clause">
    <!--
      WARNING - @mbg.generated
      This element is automatically generated by MyBatis Generator, do not modify.
    -->
    <where>
      <foreach collection="example.oredCriteria" item="criteria" separator="or">
        <if test="criteria.valid">
          <trim prefix="(" prefixOverrides="and" suffix=")">
            <foreach collection="criteria.criteria" item="criterion">
              <choose>
                <when test="criterion.noValue">
                  and ${criterion.condition}
                </when>
                <when test="criterion.singleValue">
                  and ${criterion.condition} #{criterion.value}
                </when>
                <when test="criterion.betweenValue">
                  and ${criterion.condition} #{criterion.value} and #{criterion.secondValue}
                </when>
                <when test="criterion.listValue">
                  and ${criterion.condition}
                  <foreach close=")" collection="criterion.value" item="listItem" open="(" separator=",">
                    #{listItem}
                  </foreach>
                </when>
              </choose>
            </foreach>
          </trim>
        </if>
      </foreach>
    </where>
  </sql>
  <sql id="Base_Column_List">
    <!--
      WARNING - @mbg.generated
      This element is automatically generated by MyBatis Generator, do not modify.
    -->
    id, menu_code, menu_name, permission_code, permission_name, required_permission
  </sql>
  <select id="selectByExample" parameterType="com.humingfeng.pojo.SysPermissionExample" resultMap="BaseResultMap">
    <!--
      WARNING - @mbg.generated
      This element is automatically generated by MyBatis Generator, do not modify.
    -->
    select
    <if test="distinct">
      distinct
    </if>
    <include refid="Base_Column_List" />
    from sys_permission
    <if test="_parameter != null">
      <include refid="Example_Where_Clause" />
    </if>
    <if test="orderByClause != null">
      order by ${orderByClause}
    </if>
  </select>
  <select id="selectByPrimaryKey" parameterType="java.lang.Integer" resultMap="BaseResultMap">
    <!--
      WARNING - @mbg.generated
      This element is automatically generated by MyBatis Generator, do not modify.
    -->
    select 
    <include refid="Base_Column_List" />
    from sys_permission
    where id = #{id,jdbcType=INTEGER}
  </select>
  <delete id="deleteByPrimaryKey" parameterType="java.lang.Integer">
    <!--
      WARNING - @mbg.generated
      This element is automatically generated by MyBatis Generator, do not modify.
    -->
    delete from sys_permission
    where id = #{id,jdbcType=INTEGER}
  </delete>
  <delete id="deleteByExample" parameterType="com.humingfeng.pojo.SysPermissionExample">
    <!--
      WARNING - @mbg.generated
      This element is automatically generated by MyBatis Generator, do not modify.
    -->
    delete from sys_permission
    <if test="_parameter != null">
      <include refid="Example_Where_Clause" />
    </if>
  </delete>
  <insert id="insert" parameterType="com.humingfeng.pojo.SysPermission">
    <!--
      WARNING - @mbg.generated
      This element is automatically generated by MyBatis Generator, do not modify.
    -->
    insert into sys_permission (id, menu_code, menu_name, 
      permission_code, permission_name, required_permission
      )
    values (#{id,jdbcType=INTEGER}, #{menuCode,jdbcType=VARCHAR}, #{menuName,jdbcType=VARCHAR}, 
      #{permissionCode,jdbcType=VARCHAR}, #{permissionName,jdbcType=VARCHAR}, #{requiredPermission,jdbcType=BIT}
      )
  </insert>
  <insert id="insertSelective" parameterType="com.humingfeng.pojo.SysPermission">
    <!--
      WARNING - @mbg.generated
      This element is automatically generated by MyBatis Generator, do not modify.
    -->
    insert into sys_permission
    <trim prefix="(" suffix=")" suffixOverrides=",">
      <if test="id != null">
        id,
      </if>
      <if test="menuCode != null">
        menu_code,
      </if>
      <if test="menuName != null">
        menu_name,
      </if>
      <if test="permissionCode != null">
        permission_code,
      </if>
      <if test="permissionName != null">
        permission_name,
      </if>
      <if test="requiredPermission != null">
        required_permission,
      </if>
    </trim>
    <trim prefix="values (" suffix=")" suffixOverrides=",">
      <if test="id != null">
        #{id,jdbcType=INTEGER},
      </if>
      <if test="menuCode != null">
        #{menuCode,jdbcType=VARCHAR},
      </if>
      <if test="menuName != null">
        #{menuName,jdbcType=VARCHAR},
      </if>
      <if test="permissionCode != null">
        #{permissionCode,jdbcType=VARCHAR},
      </if>
      <if test="permissionName != null">
        #{permissionName,jdbcType=VARCHAR},
      </if>
      <if test="requiredPermission != null">
        #{requiredPermission,jdbcType=BIT},
      </if>
    </trim>
  </insert>
  <select id="countByExample" parameterType="com.humingfeng.pojo.SysPermissionExample" resultType="java.lang.Long">
    <!--
      WARNING - @mbg.generated
      This element is automatically generated by MyBatis Generator, do not modify.
    -->
    select count(*) from sys_permission
    <if test="_parameter != null">
      <include refid="Example_Where_Clause" />
    </if>
  </select>
  <update id="updateByExampleSelective" parameterType="map">
    <!--
      WARNING - @mbg.generated
      This element is automatically generated by MyBatis Generator, do not modify.
    -->
    update sys_permission
    <set>
      <if test="record.id != null">
        id = #{record.id,jdbcType=INTEGER},
      </if>
      <if test="record.menuCode != null">
        menu_code = #{record.menuCode,jdbcType=VARCHAR},
      </if>
      <if test="record.menuName != null">
        menu_name = #{record.menuName,jdbcType=VARCHAR},
      </if>
      <if test="record.permissionCode != null">
        permission_code = #{record.permissionCode,jdbcType=VARCHAR},
      </if>
      <if test="record.permissionName != null">
        permission_name = #{record.permissionName,jdbcType=VARCHAR},
      </if>
      <if test="record.requiredPermission != null">
        required_permission = #{record.requiredPermission,jdbcType=BIT},
      </if>
    </set>
    <if test="_parameter != null">
      <include refid="Update_By_Example_Where_Clause" />
    </if>
  </update>
  <update id="updateByExample" parameterType="map">
    <!--
      WARNING - @mbg.generated
      This element is automatically generated by MyBatis Generator, do not modify.
    -->
    update sys_permission
    set id = #{record.id,jdbcType=INTEGER},
      menu_code = #{record.menuCode,jdbcType=VARCHAR},
      menu_name = #{record.menuName,jdbcType=VARCHAR},
      permission_code = #{record.permissionCode,jdbcType=VARCHAR},
      permission_name = #{record.permissionName,jdbcType=VARCHAR},
      required_permission = #{record.requiredPermission,jdbcType=BIT}
    <if test="_parameter != null">
      <include refid="Update_By_Example_Where_Clause" />
    </if>
  </update>
  <update id="updateByPrimaryKeySelective" parameterType="com.humingfeng.pojo.SysPermission">
    <!--
      WARNING - @mbg.generated
      This element is automatically generated by MyBatis Generator, do not modify.
    -->
    update sys_permission
    <set>
      <if test="menuCode != null">
        menu_code = #{menuCode,jdbcType=VARCHAR},
      </if>
      <if test="menuName != null">
        menu_name = #{menuName,jdbcType=VARCHAR},
      </if>
      <if test="permissionCode != null">
        permission_code = #{permissionCode,jdbcType=VARCHAR},
      </if>
      <if test="permissionName != null">
        permission_name = #{permissionName,jdbcType=VARCHAR},
      </if>
      <if test="requiredPermission != null">
        required_permission = #{requiredPermission,jdbcType=BIT},
      </if>
    </set>
    where id = #{id,jdbcType=INTEGER}
  </update>
  <update id="updateByPrimaryKey" parameterType="com.humingfeng.pojo.SysPermission">
    <!--
      WARNING - @mbg.generated
      This element is automatically generated by MyBatis Generator, do not modify.
    -->
    update sys_permission
    set menu_code = #{menuCode,jdbcType=VARCHAR},
      menu_name = #{menuName,jdbcType=VARCHAR},
      permission_code = #{permissionCode,jdbcType=VARCHAR},
      permission_name = #{permissionName,jdbcType=VARCHAR},
      required_permission = #{requiredPermission,jdbcType=BIT}
    where id = #{id,jdbcType=INTEGER}
  </update>



  <select id="getUserPermission" resultMap="permissionMap">
        SELECT
        u.id userId,
        u.nickname nickname,
        u.role_id roleId,
        r.role_name roleName,
        p.menu_code menuCode,
        p.permission_code permissionCode
        FROM sys_user u
        LEFT JOIN sys_role r ON r.id = u.role_id
        LEFT JOIN sys_role_permission rp ON u.role_id = rp.role_id
        LEFT JOIN sys_permission p ON rp.permission_id = p.id AND rp.delete_status='1'
        WHERE u.username = #{username}
        AND u.delete_status='1'
    </select>

  <select id="getAllPermission" resultType="String">
        SELECT p.permission_code permissionCode
        FROM sys_permission p
        ORDER BY p.id
    </select>
  <select id="getAllMenu" resultType="String">
        SELECT p.menu_code menuCode
        FROM sys_permission p
        ORDER BY p.id
    </select>
</mapper>